beancount_parser_lima-0.8.0.dist-info/METADATA
beancount_parser_lima-0.8.0.dist-info/WHEEL
beancount_parser_lima/__init__.py
beancount_parser_lima/beancount_parser_lima.cpython-39-x86_64-linux-gnu.so
beancount_parser_lima-0.8.0.dist-info/RECORD
