Metadata-Version: 2.4
Name: beancount-parser-lima
Version: 0.8.0
Classifier: Programming Language :: Rust
Classifier: Programming Language :: Python :: Implementation :: CPython
Classifier: Programming Language :: Python :: Implementation :: PyPy
Summary: Python bindings for beancount-parser-lima
Home-Page: https://github.com/tesujimath/beancount-parser-lima
License: Either of Apache License v2.0 or MIT License at your option
Requires-Python: >=3.7
Project-URL: Homepage, https://github.com/tesujimath/beancount-parser-lima
Project-URL: Documentation, https://github.com/tesujimath/beancount-parser-lima/blob/main/beancount-parser-lima-python/README.md
Project-URL: Repository, https://github.com/tesujimath/beancount-parser-lima
Project-URL: Issues, https://github.com/tesujimath/beancount-parser-lima/issues
